faststream_instrumentation/__about__.py
faststream_instrumentation/__init__.py
faststream_instrumentation/annotations.py
faststream_instrumentation/package.py
faststream_instrumentation/version.py
faststream_instrumentation-0.0.1.dist-info/METADATA
faststream_instrumentation-0.0.1.dist-info/WHEEL
faststream_instrumentation-0.0.1.dist-info/licenses/LICENSE.txt
faststream_instrumentation-0.0.1.dist-info/RECORD
